{
  "kind": "singleType",
  "collectionName": "configs",
  "info": {
    "singularName": "config",
    "pluralName": "configs",
    "displayName": "config",
    "description": ""
  },
  "options": {
    "draftAndPublish": false
  },
  "pluginOptions": {
    "i18n": {
      "localized": true
    }
  },
  "attributes": {
    "START_TEXT": {
      "type": "text",
      "pluginOptions": {
        "i18n": {
          "localized": true
        }
      }
    },
    "START_IMAGE": {
      "type": "media",
      "multiple": false,
      "required": false,
      "allowedTypes": [
        "images",
        "files",
        "videos",
        "audios"
      ],
      "pluginOptions": {
        "i18n": {
          "localized": true
        }
      }
    },
    "MAIN_KEYBOARD": {
      "displayName": "MAIN_KEYBOARD",
      "type": "component",
      "repeatable": false,
      "component": "keyboards.main-keyboard",
      "pluginOptions": {
        "i18n": {
          "localized": true
        }
      }
    },
    "PARTNERSHIP_KEYBOARD": {
      "type": "component",
      "repeatable": true,
      "component": "keyboards.button",
      "pluginOptions": {
        "i18n": {
          "localized": true
        }
      }
    },
    "BACK_BTN": {
      "type": "component",
      "repeatable": false,
      "pluginOptions": {
        "i18n": {
          "localized": true
        }
      },
      "component": "keyboards.button"
    },
    "SELECT_LANGUAGE_TEXT": {
      "pluginOptions": {
        "i18n": {
          "localized": false
        }
      },
      "type": "text"
    },
    "MY_PROJECT_KEYBOARD": {
      "type": "component",
      "repeatable": true,
      "pluginOptions": {
        "i18n": {
          "localized": true
        }
      },
      "component": "keyboards.button"
    },
    "ASK_QUESTION_BTN": {
      "type": "component",
      "repeatable": false,
      "pluginOptions": {
        "i18n": {
          "localized": true
        }
      },
      "component": "keyboards.button"
    },
    "HELP_ANIMALS_BTN": {
      "type": "component",
      "repeatable": false,
      "pluginOptions": {
        "i18n": {
          "localized": true
        }
      },
      "component": "keyboards.button"
    }
  }
}
